README.txt
buildout.cfg
setup.py
src/zc/__init__.py
src/zc.zookeeperrecipes.egg-info/PKG-INFO
src/zc.zookeeperrecipes.egg-info/SOURCES.txt
src/zc.zookeeperrecipes.egg-info/dependency_links.txt
src/zc.zookeeperrecipes.egg-info/entry_points.txt
src/zc.zookeeperrecipes.egg-info/namespace_packages.txt
src/zc.zookeeperrecipes.egg-info/not-zip-safe
src/zc.zookeeperrecipes.egg-info/requires.txt
src/zc.zookeeperrecipes.egg-info/top_level.txt
src/zc/zookeeperrecipes/README.txt
src/zc/zookeeperrecipes/__init__.py
src/zc/zookeeperrecipes/tests.py