Metadata-Version: 1.0
Name: zc.zookeeperrecipes
Version: 0.2.0
Summary: =================
Home-page: UNKNOWN
Author: Jim Fulton
Author-email: jim@zope.com
License: ZPL 2.1
Platform: UNKNOWN
